badook_tests/__init__.py
badook_tests/cli/__init__.py
badook_tests/cli/bdk.py
badook_tests/cli/init.py
badook_tests/cli/project.py
badook_tests/cli/run.py
badook_tests/config/__init__.py
badook_tests/config/config.py
badook_tests/config/settings.py
badook_tests/context/__init__.py
badook_tests/context/client.py
badook_tests/context/context.py
badook_tests/context/global_context.py
badook_tests/data_test_case.py
badook_tests/dsl/Cluster/__init__.py
badook_tests/dsl/Cluster/dbscan.py
badook_tests/dsl/CorrelationSummary/__init__.py
badook_tests/dsl/CorrelationSummary/pearson.py
badook_tests/dsl/CorrelationSummary/spearman.py
badook_tests/dsl/__init__.py
badook_tests/dsl/checks.py
badook_tests/dsl/enums/__init__.py
badook_tests/dsl/enums/comparison_point.py
badook_tests/dsl/enums/duplicates.py
badook_tests/dsl/enums/metadata.py
badook_tests/dsl/enums/schema.py
badook_tests/dsl/summaries/__init__.py
badook_tests/dsl/summaries/labels_summary.py
badook_tests/dsl/summaries/timeseries_analysis_summary.py
badook_tests/dsl/summaries/windowed_summaries.py
badook_tests/dsl/summary.py
badook_tests/runner.py
badook_tests/util/__init__.py
badook_tests/util/halo_multy.py
badook_tests-0.4.0rc0.dist-info/entry_points.txt
badook_tests-0.4.0rc0.dist-info/LICENSE
badook_tests-0.4.0rc0.dist-info/WHEEL
badook_tests-0.4.0rc0.dist-info/METADATA
badook_tests-0.4.0rc0.dist-info/RECORD
